{"status":"done","publicPath":"http://127.0.0.1:8080/","chunks":{"app":[{"name":"bundle.js","publicPath":"http://127.0.0.1:8080/bundle.js","path":"C:\\Workshop\\Web3Dapps\\app\\static\\dist\\bundle.js"},{"name":"app.ee5ec5bde3eca591b0ad.hot-update.js","publicPath":"http://127.0.0.1:8080/app.ee5ec5bde3eca591b0ad.hot-update.js","path":"C:\\Workshop\\Web3Dapps\\app\\static\\dist\\app.ee5ec5bde3eca591b0ad.hot-update.js"}]},"error":"ModuleError","message":"Module Error (from ./node_modules/vue-loader/lib/loaders/templateLoader.js):\n(Emitted value instead of an instance of Error) \n\n  Errors compiling template:\n\n  tag <div> has no matching end tag.\n\n  1  |  \n  2  |  \n  3  |  \n     |   \n  4  |  <div class=\"dashboard-cards\">\n     |  ^^^^^^^^^^^^^^^^^^^^^^^^^^^^^\n  5  |    <div  class=\"row row-cards\">\n"}